ac_imandrill_periship/__init__.py
acmclib/__init__.py
example_pkg/__init__.py
my_pkg/__init__.py
ac_imandrill_periship-0.0.9.dist-info/LICENSE.txt
ac_imandrill_periship-0.0.9.dist-info/METADATA
ac_imandrill_periship-0.0.9.dist-info/WHEEL
ac_imandrill_periship-0.0.9.dist-info/top_level.txt
ac_imandrill_periship-0.0.9.dist-info/RECORD
