Metadata-Version: 2.1
Name: ac-imandrill-periship
Version: 0.0.9
Summary: Transactional Email MailChimp Helper Functions
Home-page: UNKNOWN
Author: Amy Chang
Author-email: amy.chang@periship.com
License: UNKNOWN
Platform: UNKNOWN
Classifier: Programming Language :: Python :: 3
Classifier: License :: OSI Approved :: MIT License
Classifier: Operating System :: OS Independent
Requires-Python: >=3.6
Requires-Dist: mandrill
